saltext/kubernetes/__init__.py
saltext/kubernetes/version.py
saltext/kubernetes/modules/__init__.py
saltext/kubernetes/modules/k8s.py
saltext/kubernetes/modules/kubeadm.py
saltext/kubernetes/modules/kubernetesmod.py
saltext/kubernetes/states/__init__.py
saltext/kubernetes/states/kubernetesmod.py
saltext.kubernetes-1.1.0.dist-info/LICENSE
saltext.kubernetes-1.1.0.dist-info/METADATA
saltext.kubernetes-1.1.0.dist-info/NOTICE
saltext.kubernetes-1.1.0.dist-info/WHEEL
saltext.kubernetes-1.1.0.dist-info/entry_points.txt
saltext.kubernetes-1.1.0.dist-info/top_level.txt
saltext.kubernetes-1.1.0.dist-info/RECORD
