Metadata-Version: 2.2
Name: saltext.kubernetes
Version: 1.1.0
Summary: Salt Extension for interacting with Kubernetes
Author-email: "EITR Technologies, LLC" <devops@eitr.tech>
License: Apache Software License
Project-URL: Homepage, https://github.com/salt-extensions/saltext-kubernetes
Project-URL: Documentation, https://salt-extensions.github.io/saltext-kubernetes/
Project-URL: Source, https://github.com/salt-extensions/saltext-kubernetes
Project-URL: Tracker, https://github.com/salt-extensions/saltext-kubernetes/issues
Keywords: salt-extension
Platform: any
Classifier: Programming Language :: Python
Classifier: Programming Language :: Cython
Classifier: Programming Language :: Python :: 3
Classifier: Programming Language :: Python :: 3 :: Only
Classifier: Programming Language :: Python :: 3.9
Classifier: Programming Language :: Python :: 3.10
Classifier: Development Status :: 4 - Beta
Classifier: Intended Audience :: Developers
Classifier: License :: OSI Approved :: Apache Software License
Requires-Python: >=3.9
License-File: LICENSE
License-File: NOTICE
Requires-Dist: salt>=3006
Requires-Dist: kubernetes>=19.15.0; platform_system == "Linux"
Provides-Extra: changelog
Requires-Dist: towncrier==22.12.0; extra == "changelog"
Provides-Extra: dev
Requires-Dist: nox[uv]>=2024.3; extra == "dev"
Requires-Dist: pre-commit>=2.21.0; extra == "dev"
Provides-Extra: docs
Requires-Dist: sphinx; extra == "docs"
Requires-Dist: sphinx-prompt; extra == "docs"
Requires-Dist: sphinxcontrib-spelling; extra == "docs"
Requires-Dist: sphinx-copybutton; extra == "docs"
Requires-Dist: towncrier==22.12.0; extra == "docs"
Requires-Dist: sphinxcontrib-towncrier; extra == "docs"
Requires-Dist: myst_parser; extra == "docs"
Requires-Dist: furo; extra == "docs"
Requires-Dist: sphinx-inline-tabs; extra == "docs"
Provides-Extra: docsauto
Requires-Dist: sphinx-autobuild; extra == "docsauto"
Provides-Extra: lint
Requires-Dist: pylint==3.2.6; extra == "lint"
Provides-Extra: tests
Requires-Dist: pytest>=7.2.0; extra == "tests"
Requires-Dist: pytest-salt-factories>=1.0.0; extra == "tests"
Requires-Dist: pytest-custom-exit-code>=0.3; extra == "tests"
Requires-Dist: pytest-helpers-namespace>=2019.1.8; extra == "tests"
Requires-Dist: pytest-subtests; extra == "tests"
Requires-Dist: pytest-timeout; extra == "tests"
